Metadata-Version: 1.1
Name: captiv8
Version: 0.0.1
Summary: Captive Portal Evasion Tool
Home-page: http://wraith-wireless.github.io/captiv8/
Author: Dale Patterson
Author-email: wraith.wireless@yandex.com
License: GPLv3
Download-URL: https://github.com/wraith-wireless/captiv8/archive/0.0.1.tar.gz
Keywords: Linux Python pentest hacking wireless WLAN WiFi 802.11
Platform: UNKNOWN
Classifier: Development Status :: 4 - Beta
Classifier: License :: OSI Approved :: GNU General Public License v3 (GPLv3)
Classifier: Intended Audience :: Developers
Classifier: Intended Audience :: System Administrators
Classifier: Topic :: Security
Classifier: Topic :: Software Development
Classifier: Topic :: Security
Classifier: Topic :: System :: Networking
Classifier: Topic :: Utilities
Classifier: Operating System :: POSIX :: Linux
Classifier: Programming Language :: Python
Classifier: Programming Language :: Python :: 2.7
